ewoksxrdct/__init__.py
ewoksxrdct/tasks/__init__.py
ewoksxrdct/tasks/sumtask.py
ewoksxrdct/tasks/utils/__init__.py
ewoksxrdct/tests/__init__.py
ewoksxrdct/tests/conftest.py
ewoksxrdct/tests/test_sumtask.py
ewoksxrdct/tests/utils/__init__.py
ewoksxrdct-0.0.2.dist-info/licenses/LICENSE.md
orangecontrib/ewoksxrdct/__init__.py
orangecontrib/ewoksxrdct/sumtask.py
orangecontrib/ewoksxrdct/categories/__init__.py
orangecontrib/ewoksxrdct/categories/examples1/__init__.py
orangecontrib/ewoksxrdct/categories/examples1/sumtask.py
orangecontrib/ewoksxrdct/categories/examples1/icons/__init__.py
orangecontrib/ewoksxrdct/categories/examples1/icons/category.svg
orangecontrib/ewoksxrdct/categories/examples1/icons/sum.png
orangecontrib/ewoksxrdct/categories/examples1/tutorials/__init__.py
orangecontrib/ewoksxrdct/categories/examples1/tutorials/examples1.ows
orangecontrib/ewoksxrdct/categories/examples2/__init__.py
orangecontrib/ewoksxrdct/categories/examples2/sumtask.py
orangecontrib/ewoksxrdct/categories/examples2/icons/__init__.py
orangecontrib/ewoksxrdct/categories/examples2/icons/category.svg
orangecontrib/ewoksxrdct/categories/examples2/icons/sum.png
orangecontrib/ewoksxrdct/categories/examples2/tutorials/__init__.py
orangecontrib/ewoksxrdct/categories/examples2/tutorials/examples2.ows
orangecontrib/ewoksxrdct/icons/__init__.py
orangecontrib/ewoksxrdct/icons/category.svg
orangecontrib/ewoksxrdct/icons/sum.png
orangecontrib/ewoksxrdct/tutorials/__init__.py
orangecontrib/ewoksxrdct/tutorials/examples.ows
ewoksxrdct-0.0.2.dist-info/METADATA
ewoksxrdct-0.0.2.dist-info/WHEEL
ewoksxrdct-0.0.2.dist-info/entry_points.txt
ewoksxrdct-0.0.2.dist-info/top_level.txt
ewoksxrdct-0.0.2.dist-info/RECORD
