Metadata-Version: 2.4
Name: ewoksxrdct
Version: 0.0.2
Summary: An Ewoks project
Author-email: ESRF <dau-pydev@esrf.fr>
License: # MIT License
Project-URL: Homepage, https://gitlab.esrf.fr/workflow/ewoksapps/ewoksxrdct/
Project-URL: Documentation, https://ewoksxrdct.readthedocs.io/
Project-URL: Repository, https://gitlab.esrf.fr/workflow/ewoksapps/ewoksxrdct/
Project-URL: Issues, https://gitlab.esrf.fr/workflow/ewoksapps/ewoksxrdct/issues
Project-URL: Changelog, https://gitlab.esrf.fr/workflow/ewoksapps/ewoksxrdct/-/blob/main/CHANGELOG.md
Keywords: orange3 add-on,ewoks
Classifier: Intended Audience :: Science/Research
Classifier: License :: OSI Approved :: MIT License
Classifier: Programming Language :: Python :: 3
Requires-Python: >=3.10
License-File: LICENSE.md
Requires-Dist: ewoksorange
Requires-Dist: nexusformat
Provides-Extra: test
Requires-Dist: pytest>=7; extra == "test"
Requires-Dist: pyqt5; extra == "test"
Provides-Extra: dev
Requires-Dist: ewoksxrdct[test]; extra == "dev"
Requires-Dist: black>=25; extra == "dev"
Requires-Dist: flake8>=4; extra == "dev"
Requires-Dist: ruff; extra == "dev"
Requires-Dist: bandit; extra == "dev"
Requires-Dist: isort; extra == "dev"
Provides-Extra: doc
Requires-Dist: ewoksxrdct[test]; extra == "doc"
Requires-Dist: sphinx>=4.5; extra == "doc"
Requires-Dist: sphinx-autodoc-typehints>=1.16; extra == "doc"
Requires-Dist: pydata-sphinx-theme; extra == "doc"
Requires-Dist: myst-parser; extra == "doc"
Dynamic: license-file
